mail2cospend/__init__.py
mail2cospend/config.py
mail2cospend/cospendconnector.py
mail2cospend/data.py
mail2cospend/helper.py
mail2cospend/mailconnector.py
mail2cospend/main.py
mail2cospend/ntfy.py
mail2cospend/searchadapter/__init__.py
mail2cospend/searchadapter/edeka.py
mail2cospend/searchadapter/ikea.py
mail2cospend/searchadapter/kokku.py
mail2cospend/searchadapter/netto.py
mail2cospend/searchadapter/picnic.py
mail2cospend/searchadapter/planted.py
mail2cospend/searchadapter/rewe.py
mail2cospend/searchadapter/searchadapter.py
mail2cospend-0.5.3.dist-info/METADATA
mail2cospend-0.5.3.dist-info/WHEEL
mail2cospend-0.5.3.dist-info/entry_points.txt
mail2cospend-0.5.3.dist-info/licenses/LICENSE
mail2cospend-0.5.3.dist-info/RECORD
