Metadata-Version: 2.4
Name: mail2cospend
Version: 0.5.3
Summary: Send summaries of eBons (Rewe, Netto, ..) to cospend.
Project-URL: Homepage, https://github.com/joleaf/mail2cospend
Project-URL: Documentation, https://github.com/joleaf/mail2cospend
Project-URL: Repository, https://github.com/joleaf/mail2cospend
Project-URL: Issues, https://github.com/joleaf/mail2cospend/issues
Author-email: Jonas Blatt <jonas@blatts.de>
License:                     GNU GENERAL PUBLIC LICENSE
License-File: LICENSE
Keywords: cospend,eBon,imap,ntfy,workflow
Requires-Python: >=3.12
Requires-Dist: click>=8.1.7
Requires-Dist: pypdf2>=3.0.1
Requires-Dist: python-dotenv>=1.0.1
Requires-Dist: pyyaml>=6.0.2
Requires-Dist: requests>=2.32.3
